dosei/__init__.py
dosei/app.py
dosei/importer.py
dosei/integrations/__init__.py
dosei/integrations/fastapi.py
dosei/main.py
dosei/schemas/cron_jobs.py
dosei-0.0.17.dist-info/LICENSE
dosei-0.0.17.dist-info/METADATA
dosei-0.0.17.dist-info/WHEEL
dosei-0.0.17.dist-info/entry_points.txt
dosei-0.0.17.dist-info/RECORD
