Metadata-Version: 2.1
Name: dosei
Version: 0.0.17
Summary: Dosei Python SDK
License: Apache-2.0
Author: Alvaro Molina
Author-email: am@dosei.ai
Requires-Python: >=3.11,<4.0
Classifier: License :: OSI Approved :: Apache Software License
Classifier: Programming Language :: Python :: 3
Classifier: Programming Language :: Python :: 3.11
Classifier: Programming Language :: Python :: 3.12
Requires-Dist: click (>=8.1.7,<9.0.0)
Requires-Dist: croniter (>=2.0.1,<3.0.0)
Requires-Dist: dosei-util (>=0.0.1,<0.0.2)
Requires-Dist: fastapi (>=0.104.1,<0.105.0)
Requires-Dist: pydantic (>=2.5.1,<3.0.0)
Requires-Dist: pytest-trio (>=0.8.0,<0.9.0)
